vec3/__init__.py
vec3/vec3.py
vec3-0.1.0.dist-info/LICENSE
vec3-0.1.0.dist-info/METADATA
vec3-0.1.0.dist-info/WHEEL
vec3-0.1.0.dist-info/top_level.txt
vec3-0.1.0.dist-info/RECORD
